kahi_minciencias_opendata_works_misc/Kahi_minciencias_opendata_works_misc.py
kahi_minciencias_opendata_works_misc/__init__.py
kahi_minciencias_opendata_works_misc/_version.py
kahi_minciencias_opendata_works_misc/parser.py
kahi_minciencias_opendata_works_misc/process_one.py
Kahi_minciencias_opendata_works_misc-0.1.0b0.dist-info/LICENSE
Kahi_minciencias_opendata_works_misc-0.1.0b0.dist-info/METADATA
Kahi_minciencias_opendata_works_misc-0.1.0b0.dist-info/WHEEL
Kahi_minciencias_opendata_works_misc-0.1.0b0.dist-info/top_level.txt
Kahi_minciencias_opendata_works_misc-0.1.0b0.dist-info/RECORD
