Metadata-Version: 2.2
Name: Kahi_minciencias_opendata_works_misc
Version: 0.1.0b0
Summary: Kahi plugin to insert and update works misc from minciencias opendata
Home-page: https://github.com/colav/Kahi_plugins
Author: Colav
Author-email: colav@udea.edu.co
License: BSD
License-File: LICENSE
Requires-Dist: kahi
Requires-Dist: pymongo
Requires-Dist: joblib
Requires-Dist: kahi_impactu_utils
Requires-Dist: mohan
Dynamic: author
Dynamic: author-email
Dynamic: description
Dynamic: description-content-type
Dynamic: home-page
Dynamic: license
Dynamic: requires-dist
Dynamic: summary
